Workbook
Name SlicerCache_Table_1_Col_9: #N/A

Sheet Problem Statement
A1: Scenario
A2: You're a junior data analyst at a 50-person company. HR has handed you a raw employee export and needs a clean, automated payroll summary report.
A4: Dataset to build
A5: Sheet: Employees — EmpID, Name, Department, Role, JoinDate, Salary, HoursWorked (weekly avg), Rating (1–5), Region
A6: Sheet: TaxBrackets — MinSalary, MaxSalary, TaxRate%
A7: 50 rows of employee data across 5 departments, 3 regions
A9: Tasks | B9: Status
A10: Use XLOOKUP to pull each employee's tax rate from TaxBrackets and calculate net salary. | B10: Done
A11: Add a Tenure column using date functions (years since JoinDate). | B11: Done
A12: Flag employees as "High Performer", "Needs Review", or "Standard" using IFS based on Rating + Tenure combination. | B12: Done
A13: Use COUNTIFS / AVERAGEIFS / SUMIFS to build a Department Summary table: headcount, avg salary, avg rating per dept. | B13: Done
A14: Rank employees within their department by salary using RANK with absolute references. | B14: Done
A15: Apply conditional formatting: red for Rating < 2, green for Rating ≥ 4, salary heatmap. | B15: Done
A16: Build a Pivot Table: avg salary by Department × Region, with a slicer on Region. | B16: Done
A17: Create a bar chart of avg salary by department and a sparkline showing salary distribution per dept. | B17: Done
A18: Add a What-If Data Table: show total payroll cost if all salaries are raised by 0%, 5%, 10%, 15%. | B18: Done

Sheet Employees
A1: EmpID | B1: Name | C1: Department | D1: Role | E1: JoinDate | F1: Salary | G1: HoursWorked | H1: Rating | I1: Region
A2: EMP1001 | B2: Saurav Gupta | C2: Engineering | D2: Junior Dev | E2: 42964 | F2: 83000 | G2: 36.4 | H2: 2 | I2: North
A3: EMP1002 | B3: Rekha Jadhav | C3: Engineering | D3: Junior Dev | E3: 43583 | F3: 93000 | G3: 32.6 | H3: 1.8 | I3: North
A4: EMP1003 | B4: Ayaan Trivedi | C4: Engineering | D4: Junior Dev | E4: 43703 | F4: 78000 | G4: 44.9 | H4: 4 | I4: South
A5: EMP1004 | B5: Rahul Bhat | C5: Engineering | D5: QA Engineer | E5: 42686 | F5: 122000 | G5: 32.1 | H5: 4.3 | I5: West
A6: EMP1005 | B6: Harsh Mishra | C6: Engineering | D6: QA Engineer | E6: 45365 | F6: 79000 | G6: 49.2 | H6: 2.7 | I6: North
A7: EMP1006 | B7: Simran Verma | C7: Engineering | D7: QA Engineer | E7: 44593 | F7: 105000 | G7: 36.8 | H7: 1.7 | I7: South
A8: EMP1007 | B8: Raj Gupta | C8: Engineering | D8: DevOps Engineer | E8: 45679 | F8: 101000 | G8: 37.3 | H8: 3.7 | I8: South
A9: EMP1008 | B9: Akash Iyer | C9: Engineering | D9: Junior Dev | E9: 45814 | F9: 108000 | G9: 36.1 | H9: 2.5 | I9: North
A10: EMP1009 | B10: Rahul Verma | C10: Engineering | D10: DevOps Engineer | E10: 44863 | F10: 95000 | G10: 43.4 | H10: 2.8 | I10: South
A11: EMP1010 | B11: Nisha Bose | C11: Engineering | D11: QA Engineer | E11: 43127 | F11: 126000 | G11: 44.3 | H11: 1.7 | I11: West
A12: EMP1011 | B12: Siddharth Saxena | C12: Sales | D12: Account Manager | E12: 45332 | F12: 75000 | G12: 38.8 | H12: 5 | I12: West
A13: EMP1012 | B13: Gaurav Bhatnagar | C13: Sales | D13: Account Manager | E13: 43197 | F13: 66000 | G13: 47.2 | H13: 4.2 | I13: North
... A51: EMP1050 | B51: Harsh Shah | C51: HR | D51: HR Coordinator | E51: 44739 | F51: 62000 | G51: 48.2 | H51: 4.3 | I51: North

Sheet TaxBrackets
A1: MinSalary | B1: MaxSalary | C1: TaxRate%
A2: 0 | B2: 29999 | C2: 0
A3: 30000 | B3: 49999 | C3: 10
A4: 50000 | B4: 74999 | C4: 20
A5: 75000 | B5: 99999 | C5: 28
A6: 100000 | B6: 999999 | C6: 35

Sheet 1
A1: Emp Name | B1: Salary | C1: Tax Bracket (%) | D1: Net Salary | G1: Use XLOOKUP to pull each employee's tax rate from TaxBrackets and calculate net salary.
A2: {=Employees!B2:B51} -> Saurav Gupta | B2: {=Employees!F2:F51} -> 83000 | C2: =(_xlfn.XLOOKUP(B2,TaxBrackets!$A$2:$A$6,TaxBrackets!$C$2:$C$6,"Not Found",-1))/100 -> 0.28 | D2: =(B2*C2)+B2 -> 106240
A3: Rekha Jadhav | B3: 93000 | C3: =(_xlfn.XLOOKUP(B3,TaxBrackets!$A$2:$A$6,TaxBrackets!$C$2:$C$6,"Not Found",-1))/100 -> 0.28 | D3: =(B3*C3)+B3 -> 119040
A4: Ayaan Trivedi | B4: 78000 | C4: =(_xlfn.XLOOKUP(B4,TaxBrackets!$A$2:$A$6,TaxBrackets!$C$2:$C$6,"Not Found",-1))/100 -> 0.28 | D4: =(B4*C4)+B4 -> 99840
A5: Rahul Bhat | B5: 122000 | C5: =(_xlfn.XLOOKUP(B5,TaxBrackets!$A$2:$A$6,TaxBrackets!$C$2:$C$6,"Not Found",-1))/100 -> 0.35 | D5: =(B5*C5)+B5 -> 164700
A6: Harsh Mishra | B6: 79000 | C6: =(_xlfn.XLOOKUP(B6,TaxBrackets!$A$2:$A$6,TaxBrackets!$C$2:$C$6,"Not Found",-1))/100 -> 0.28 | D6: =(B6*C6)+B6 -> 101120
A7: Simran Verma | B7: 105000 | C7: =(_xlfn.XLOOKUP(B7,TaxBrackets!$A$2:$A$6,TaxBrackets!$C$2:$C$6,"Not Found",-1))/100 -> 0.35 | D7: =(B7*C7)+B7 -> 141750
A8: Raj Gupta | B8: 101000 | C8: =(_xlfn.XLOOKUP(B8,TaxBrackets!$A$2:$A$6,TaxBrackets!$C$2:$C$6,"Not Found",-1))/100 -> 0.35 | D8: =(B8*C8)+B8 -> 136350
A9: Akash Iyer | B9: 108000 | C9: =(_xlfn.XLOOKUP(B9,TaxBrackets!$A$2:$A$6,TaxBrackets!$C$2:$C$6,"Not Found",-1))/100 -> 0.35 | D9: =(B9*C9)+B9 -> 145800
A10: Rahul Verma | B10: 95000 | C10: =(_xlfn.XLOOKUP(B10,TaxBrackets!$A$2:$A$6,TaxBrackets!$C$2:$C$6,"Not Found",-1))/100 -> 0.28 | D10: =(B10*C10)+B10 -> 121600
A11: Nisha Bose | B11: 126000 | C11: =(_xlfn.XLOOKUP(B11,TaxBrackets!$A$2:$A$6,TaxBrackets!$C$2:$C$6,"Not Found",-1))/100 -> 0.35 | D11: =(B11*C11)+B11 -> 170100
A12: Siddharth Saxena | B12: 75000 | C12: =(_xlfn.XLOOKUP(B12,TaxBrackets!$A$2:$A$6,TaxBrackets!$C$2:$C$6,"Not Found",-1))/100 -> 0.28 | D12: =(B12*C12)+B12 -> 96000
A13: Gaurav Bhatnagar | B13: 66000 | C13: =(_xlfn.XLOOKUP(B13,TaxBrackets!$A$2:$A$6,TaxBrackets!$C$2:$C$6,"Not Found",-1))/100 -> 0.2 | D13: =(B13*C13)+B13 -> 79200
A14: Rohan Sinha | B14: 49000 | C14: =(_xlfn.XLOOKUP(B14,TaxBrackets!$A$2:$A$6,TaxBrackets!$C$2:$C$6,"Not Found",-1))/100 -> 0.1 | D14: =(B14*C14)+B14 -> 53900
... A51: Harsh Shah | B51: 62000 | C51: =(_xlfn.XLOOKUP(B51,TaxBrackets!$A$2:$A$6,TaxBrackets!$C$2:$C$6,"Not Found",-1))/100 -> 0.2 | D51: =(B51*C51)+B51 -> 74400

Sheet 2
A1: Name | B1: JoinDate | C1: Tenure [In Years] | E1: Add a Tenure column using date functions (years since JoinDate).
A2: Saurav Gupta | B2: 42964 | C2: =DATEDIF(B2,TODAY(),"Y") -> 8
A3: Rekha Jadhav | B3: 43583 | C3: =DATEDIF(B3,TODAY(),"M") -> 85
A4: Ayaan Trivedi | B4: 43703 | C4: =DATEDIF(B4,TODAY(),"Y") -> 6
A5: Rahul Bhat | B5: 42686 | C5: =DATEDIF(B5,TODAY(),"Y") -> 9
A6: Harsh Mishra | B6: 45365 | C6: =DATEDIF(B6,TODAY(),"Y") -> 2
A7: Simran Verma | B7: 44593 | C7: =DATEDIF(B7,TODAY(),"Y") -> 4
A8: Raj Gupta | B8: 45679 | C8: =DATEDIF(B8,TODAY(),"Y") -> 1
A9: Akash Iyer | B9: 45814 | C9: =DATEDIF(B9,TODAY(),"Y") -> 1
A10: Rahul Verma | B10: 44863 | C10: =DATEDIF(B10,TODAY(),"Y") -> 3
A11: Nisha Bose | B11: 43127 | C11: =DATEDIF(B11,TODAY(),"Y") -> 8
A12: Siddharth Saxena | B12: 45332 | C12: =DATEDIF(B12,TODAY(),"Y") -> 2
A13: Gaurav Bhatnagar | B13: 43197 | C13: =DATEDIF(B13,TODAY(),"Y") -> 8
A14: Rohan Sinha | B14: 44905 | C14: =DATEDIF(B14,TODAY(),"Y") -> 3
A15: Kunal Bose | B15: 44381 | C15: =DATEDIF(B15,TODAY(),"Y") -> 4
... A51: Harsh Shah | B51: 44739 | C51: =DATEDIF(B51,TODAY(),"Y") -> 3

Sheet 3
A1: Name | B1: Rating | C1: Tenure | D1: Flag | F1: Flag employees as "High Performer", "Needs Review", or "Standard" using IFS based on Rating + Tenure combination.
A2: Saurav Gupta | B2: 2 | C2: ='2'!C2:C52 -> 8 | D2: =_xlfn.IFS(AND(B2<=2,C2<=3),"Needs Review",AND(B2<=3,C2<=5),"Standard",AND(B2>=4,C2>=7),"High Performer",TRUE,"Mixed") -> Mixed
A3: Rekha Jadhav | B3: 1.8 | C3: ='2'!C3:C53 -> 85 | D3: =_xlfn.IFS(AND(B3<=2,C3<=3),"Needs Review",AND(B3<=3,C3<=5),"Standard",AND(B3>=4,C3>=7),"High Performer",TRUE,"Mixed") -> Mixed
A4: Ayaan Trivedi | B4: 4 | C4: ='2'!C4:C54 -> 6 | D4: =_xlfn.IFS(AND(B4<=2,C4<=3),"Needs Review",AND(B4<=3,C4<=5),"Standard",AND(B4>=4,C4>=7),"High Performer",TRUE,"Mixed") -> Mixed
A5: Rahul Bhat | B5: 4.3 | C5: ='2'!C5:C55 -> 9 | D5: =_xlfn.IFS(AND(B5<=2,C5<=3),"Needs Review",AND(B5<=3,C5<=5),"Standard",AND(B5>=4,C5>=7),"High Performer",TRUE,"Mixed") -> High Performer
A6: Harsh Mishra | B6: 2.7 | C6: ='2'!C6:C56 -> 2 | D6: =_xlfn.IFS(AND(B6<=2,C6<=3),"Needs Review",AND(B6<=3,C6<=5),"Standard",AND(B6>=4,C6>=7),"High Performer",TRUE,"Mixed") -> Standard
A7: Simran Verma | B7: 1.7 | C7: ='2'!C7:C57 -> 4 | D7: =_xlfn.IFS(AND(B7<=2,C7<=3),"Needs Review",AND(B7<=3,C7<=5),"Standard",AND(B7>=4,C7>=7),"High Performer",TRUE,"Mixed") -> Standard
A8: Raj Gupta | B8: 3.7 | C8: ='2'!C8:C58 -> 1 | D8: =_xlfn.IFS(AND(B8<=2,C8<=3),"Needs Review",AND(B8<=3,C8<=5),"Standard",AND(B8>=4,C8>=7),"High Performer",TRUE,"Mixed") -> Mixed
A9: Akash Iyer | B9: 2.5 | C9: ='2'!C9:C59 -> 1 | D9: =_xlfn.IFS(AND(B9<=2,C9<=3),"Needs Review",AND(B9<=3,C9<=5),"Standard",AND(B9>=4,C9>=7),"High Performer",TRUE,"Mixed") -> Standard
A10: Rahul Verma | B10: 2.8 | C10: ='2'!C10:C60 -> 3 | D10: =_xlfn.IFS(AND(B10<=2,C10<=3),"Needs Review",AND(B10<=3,C10<=5),"Standard",AND(B10>=4,C10>=7),"High Performer",TRUE,"Mixed") -> Standard
A11: Nisha Bose | B11: 1.7 | C11: ='2'!C11:C61 -> 8 | D11: =_xlfn.IFS(AND(B11<=2,C11<=3),"Needs Review",AND(B11<=3,C11<=5),"Standard",AND(B11>=4,C11>=7),"High Performer",TRUE,"Mixed") -> Mixed
A12: Siddharth Saxena | B12: 5 | C12: ='2'!C12:C62 -> 2 | D12: =_xlfn.IFS(AND(B12<=2,C12<=3),"Needs Review",AND(B12<=3,C12<=5),"Standard",AND(B12>=4,C12>=7),"High Performer",TRUE,"Mixed") -> Mixed
A13: Gaurav Bhatnagar | B13: 4.2 | C13: ='2'!C13:C63 -> 8 | D13: =_xlfn.IFS(AND(B13<=2,C13<=3),"Needs Review",AND(B13<=3,C13<=5),"Standard",AND(B13>=4,C13>=7),"High Performer",TRUE,"Mixed") -> High Performer
... A51: Harsh Shah | B51: 4.3 | C51: ='2'!C51:C101 -> 3 | D51: =_xlfn.IFS(AND(B51<=2,C51<=3),"Needs Review",AND(B51<=3,C51<=5),"Standard",AND(B51>=4,C51>=7),"High Performer",TRUE,"Mixed") -> Mixed

Sheet 4
A1: Name | B1: Department | C1: Salary | D1: Rating | G1: Use COUNTIFS / AVERAGEIFS / SUMIFS to build a Department Summary table: headcount, avg salary, avg rating per dept.
A2: Saurav Gupta | B2: Engineering | C2: 83000 | D2: 2
A3: Rekha Jadhav | B3: Engineering | C3: 93000 | D3: 1.8 | G3: Department Summary Table
A4: Ayaan Trivedi | B4: Engineering | C4: 78000 | D4: 4 | G4: Departments | H4: Headcount | I4: Avg Salary | J4: Avg Rating
A5: Rahul Bhat | B5: Engineering | C5: 122000 | D5: 4.3 | G5: {=_xlfn.UNIQUE(B2:B51)} -> Engineering | H5: =COUNTIF(B2:B51,G5) -> 10 | I5: =AVERAGEIF(B2:B51,G5,C2:C51) -> 99000 | J5: =AVERAGEIF(B2:B51,G5,D2:D51) -> 2.72
A6: Harsh Mishra | B6: Engineering | C6: 79000 | D6: 2.7 | G6: Sales | H6: =COUNTIF(B3:B52,G6) -> 10 | I6: =AVERAGEIF(B3:B52,G6,C3:C52) -> 71200 | J6: =AVERAGEIF(B3:B52,G6,D3:D52) -> 3.56
A7: Simran Verma | B7: Engineering | C7: 105000 | D7: 1.7 | G7: Marketing | H7: =COUNTIF(B4:B53,G7) -> 10 | I7: =AVERAGEIF(B4:B53,G7,C4:C53) -> 64800 | J7: =AVERAGEIF(B4:B53,G7,D4:D53) -> 3.18
A8: Raj Gupta | B8: Engineering | C8: 101000 | D8: 3.7 | G8: Operations | H8: =COUNTIF(B5:B54,G8) -> 10 | I8: =AVERAGEIF(B5:B54,G8,C5:C54) -> 63200 | J8: =AVERAGEIF(B5:B54,G8,D5:D54) -> 3.29
A9: Akash Iyer | B9: Engineering | C9: 108000 | D9: 2.5 | G9: HR | H9: =COUNTIF(B6:B55,G9) -> 10 | I9: =AVERAGEIF(B6:B55,G9,C6:C55) -> 60800 | J9: =AVERAGEIF(B6:B55,G9,D6:D55) -> 3.28
A10: Rahul Verma | B10: Engineering | C10: 95000 | D10: 2.8
A11: Nisha Bose | B11: Engineering | C11: 126000 | D11: 1.7
A12: Siddharth Saxena | B12: Sales | C12: 75000 | D12: 5
A13: Gaurav Bhatnagar | B13: Sales | C13: 66000 | D13: 4.2
A14: Rohan Sinha | B14: Sales | C14: 49000 | D14: 4.8
A15: Kunal Bose | B15: Sales | C15: 87000 | D15: 2.4
A16: Heena Bhatnagar | B16: Sales | C16: 83000 | D16: 3.5
A17: Rahul Shah | B17: Sales | C17: 95000 | D17: 1.9
A18: Siddharth Gaikwad | B18: Sales | C18: 49000 | D18: 3.6
A19: Leena Ghosh | B19: Sales | C19: 92000 | D19: 4.6
A20: Jyoti Jain | B20: Sales | C20: 64000 | D20: 3.1
A21: Nitin Ghosh | B21: Sales | C21: 52000 | D21: 2.5
... A51: Harsh Shah | B51: HR | C51: 62000 | D51: 4.3

Sheet 5
A1: Name | B1: Department | C1: Salary | D1: Rank (Based on salary) | F1: Rank employees within their department by salary using RANK with absolute references.
A2: Nisha Bose | B2: Engineering | C2: 126000 | D2: =_xlfn.RANK.AVG(C2,$C$2:$C$51,0) -> 1
A3: Rahul Bhat | B3: Engineering | C3: 122000 | D3: =_xlfn.RANK.AVG(C3,$C$2:$C$51,0) -> 2
A4: Akash Iyer | B4: Engineering | C4: 108000 | D4: =_xlfn.RANK.AVG(C4,$C$2:$C$51,0) -> 3
A5: Simran Verma | B5: Engineering | C5: 105000 | D5: =_xlfn.RANK.AVG(C5,$C$2:$C$51,0) -> 4
A6: Raj Gupta | B6: Engineering | C6: 101000 | D6: =_xlfn.RANK.AVG(C6,$C$2:$C$51,0) -> 5
A7: Rahul Verma | B7: Engineering | C7: 95000 | D7: =_xlfn.RANK.AVG(C7,$C$2:$C$51,0) -> 6.5
A8: Rahul Shah | B8: Sales | C8: 95000 | D8: =_xlfn.RANK.AVG(C8,$C$2:$C$51,0) -> 6.5
A9: Rekha Jadhav | B9: Engineering | C9: 93000 | D9: =_xlfn.RANK.AVG(C9,$C$2:$C$51,0) -> 8
A10: Leena Ghosh | B10: Sales | C10: 92000 | D10: =_xlfn.RANK.AVG(C10,$C$2:$C$51,0) -> 9
A11: Kunal Bose | B11: Sales | C11: 87000 | D11: =_xlfn.RANK.AVG(C11,$C$2:$C$51,0) -> 10
A12: Alok Saxena | B12: Marketing | C12: 85000 | D12: =_xlfn.RANK.AVG(C12,$C$2:$C$51,0) -> 11.5
A13: Ananya Iyer | B13: Marketing | C13: 85000 | D13: =_xlfn.RANK.AVG(C13,$C$2:$C$51,0) -> 11.5
... A51: Meera Kumar | B51: HR | C51: 40000 | D51: =_xlfn.RANK.AVG(C51,$C$2:$C$51,0) -> 50

Sheet 6
A1: Name | B1: Salary | C1: Rating | D1: Rating < 2 = Red, > 4 = Green, 2 - 4 Blue | F1: Apply conditional formatting: red for Rating < 2, green for Rating ≥ 4, salary heatmap.
A2: Saurav Gupta | B2: 83000 | C2: 2
A3: Rekha Jadhav | B3: 93000 | C3: 1.8
A4: Ayaan Trivedi | B4: 78000 | C4: 4
A5: Rahul Bhat | B5: 122000 | C5: 4.3
A6: Harsh Mishra | B6: 79000 | C6: 2.7
A7: Simran Verma | B7: 105000 | C7: 1.7
A8: Raj Gupta | B8: 101000 | C8: 3.7
A9: Akash Iyer | B9: 108000 | C9: 2.5
A10: Rahul Verma | B10: 95000 | C10: 2.8
A11: Nisha Bose | B11: 126000 | C11: 1.7
A12: Siddharth Saxena | B12: 75000 | C12: 5
A13: Gaurav Bhatnagar | B13: 66000 | C13: 4.2
... A51: Harsh Shah | B51: 62000 | C51: 4.3

Sheet 7
A2: Department | B2: Region | C2: AVERAGE of Salary
A3: Engineering | B3: North | C3: 90750 | H3: Build a Pivot Table: avg salary by Department × Region, with a slicer on Region.
B4: South | C4: 94750
B5: West | C5: 124000
A6: Engineering Total | C6: 99000
A7: HR | B7: North | C7: 60875
B8: South | C8: 60500
A9: HR Total | C9: 60800
A10: Marketing | B10: North | C10: 59666.667
B11: South | C11: 67800
B12: West | C12: 65000
A13: Marketing Total | C13: 64800
A14: Operations | B14: North | C14: 55500
B15: South | C15: 63750
B16: West | C16: 66500
A17: Operations Total | C17: 63200
A18: Sales | B18: North | C18: 76500
B19: South | C19: 74666.667
B20: West | C20: 67000
A21: Sales Total | C21: 71200
A22: Grand Total | C22: 71800

Sheet 8
A1: Name | B1: Department | C1: Salary
A2: Saurav Gupta | B2: Engineering | C2: 83000 | E2: Department | F2: AVERAGE of Salary | G2: Sparkline
A3: Rekha Jadhav | B3: Engineering | C3: 93000 | E3: Engineering | F3: 99000 | I3: Create a bar chart of avg salary by department and a sparkline showing salary distribution per dept.
A4: Ayaan Trivedi | B4: Engineering | C4: 78000 | E4: HR | F4: 71200
A5: Rahul Bhat | B5: Engineering | C5: 122000 | E5: Marketing | F5: 64800
A6: Harsh Mishra | B6: Engineering | C6: 79000 | E6: Operations | F6: 63200
A7: Simran Verma | B7: Engineering | C7: 105000 | E7: Sales | F7: 60800
A8: Raj Gupta | B8: Engineering | C8: 101000 | E8: Grand Total | F8: 71800
A9: Akash Iyer | B9: Engineering | C9: 108000
A10: Rahul Verma | B10: Engineering | C10: 95000
A11: Nisha Bose | B11: Engineering | C11: 126000
A12: Siddharth Saxena | B12: HR | C12: 75000
A13: Gaurav Bhatnagar | B13: HR | C13: 66000
A14: Rohan Sinha | B14: HR | C14: 49000
A15: Kunal Bose | B15: HR | C15: 87000
A16: Heena Bhatnagar | B16: HR | C16: 83000
A17: Rahul Shah | B17: HR | C17: 95000
A18: Siddharth Gaikwad | B18: HR | C18: 49000
A19: Leena Ghosh | B19: HR | C19: 92000
A20: Jyoti Jain | B20: HR | C20: 64000
... A51: Harsh Shah | B51: Sales | C51: 62000

Sheet 9
A1: Name | B1: Salary | C1: Raise (0%) | D1: Raise (5%) | E1: Raise (10%) | F1: Raise (15%) | I1: Add a What-If Data Table: show total payroll cost if all salaries are raised by 0%, 5%, 10%, 15%.
B2: =I6 -> 46000 | C2: 0 | D2: 0.05 | E2: 0.1 | F2: 0.15
A3: Meera Kumar | B3: 40000 | C3: 40000 | D3: 42000 | E3: 44000 | F3: 46000
A4: Aarav Trivedi | B4: 43000 | C4: 43000 | D4: 45150 | E4: 47300 | F4: 49450 | H4: Salary | I4: 40000
A5: Leena Nair | B5: 45000 | C5: 45000 | D5: 47250 | E5: 49500 | F5: 51750 | H5: Raise | I5: 0.15
A6: Sneha Singh | B6: 47000 | C6: 47000 | D6: 49350 | E6: 51700 | F6: 54050 | H6: Total Slary | I6: =(I4*I5)+I4 -> 46000
A7: Rahul Kumar | B7: 47000 | C7: 47000 | D7: 49350 | E7: 51700 | F7: 54050
A8: Vikram Roy | B8: 48000 | C8: 48000 | D8: 50400 | E8: 52800 | F8: 55200
A9: Rohan Sinha | B9: 49000 | C9: 49000 | D9: 51450 | E9: 53900 | F9: 56350
A10: Siddharth Gaikwad | B10: 49000 | C10: 49000 | D10: 51450 | E10: 53900 | F10: 56350 | H10: s
A11: Nitin Ghosh | B11: 52000 | C11: 52000 | D11: 54600 | E11: 57200 | F11: 59800
A12: Dev Agarwal | B12: 52000 | C12: 52000 | D12: 54600 | E12: 57200 | F12: 59800
A13: Nikhil Reddy | B13: 53000 | C13: 53000 | D13: 55650 | E13: 58300 | F13: 60950
A14: Anjali Shukla | B14: 53000 | C14: 53000 | D14: 55650 | E14: 58300 | F14: 60950
A15: Smita Mishra | B15: 55000 | C15: 55000 | D15: 57750 | E15: 60500 | F15: 63250
A16: Ishaan Patel | B16: 56000 | C16: 56000 | D16: 58800 | E16: 61600 | F16: 64400
A17: Anjali Kulkarni | B17: 56000 | C17: 56000 | D17: 58800 | E17: 61600 | F17: 64400
A18: Varun Shah | B18: 59000 | C18: 59000 | D18: 61950 | E18: 64900 | F18: 67850
A19: Heena Saxena | B19: 61000 | C19: 61000 | D19: 64050 | E19: 67100 | F19: 70150
A20: Harsh Shah | B20: 62000 | C20: 62000 | D20: 65100 | E20: 68200 | F20: 71300
A21: Jyoti Jain | B21: 64000 | C21: 64000 | D21: 67200 | E21: 70400 | F21: 73600
A22: Gaurav Bhatnagar | B22: 66000 | C22: 66000 | D22: 69300 | E22: 72600 | F22: 75900
... A52: Nisha Bose | B52: 126000 | C52: 126000 | D52: 132300 | E52: 138600 | F52: 144900
